ape_vyper/__init__.py
ape_vyper/_cli.py
ape_vyper/_utils.py
ape_vyper/ast.py
ape_vyper/config.py
ape_vyper/coverage.py
ape_vyper/exceptions.py
ape_vyper/flattener.py
ape_vyper/imports.py
ape_vyper/interface.py
ape_vyper/py.typed
ape_vyper/traceback.py
ape_vyper/version.py
ape_vyper/compiler/__init__.py
ape_vyper/compiler/api.py
ape_vyper/compiler/_versions/__init__.py
ape_vyper/compiler/_versions/base.py
ape_vyper/compiler/_versions/utils.py
ape_vyper/compiler/_versions/vyper_02.py
ape_vyper/compiler/_versions/vyper_03.py
ape_vyper/compiler/_versions/vyper_04.py
ape_vyper-0.8.10.dist-info/licenses/LICENSE
ape_vyper-0.8.10.dist-info/METADATA
ape_vyper-0.8.10.dist-info/WHEEL
ape_vyper-0.8.10.dist-info/entry_points.txt
ape_vyper-0.8.10.dist-info/top_level.txt
ape_vyper-0.8.10.dist-info/RECORD
