Metadata-Version: 2.4
Name: ape-vyper
Version: 0.8.10
Summary: ape-vyper: Ape Framework plugin for compiling Vyper contracts
Author-email: "ApeWorX Ltd." <admin@apeworx.io>
License-Expression: Apache-2.0
Project-URL: Repository, https://github.com/ApeWorX/ape-vyper
Project-URL: Issues, https://github.com/ApeWorX/ape-vyper/issues
Project-URL: Documentation, https://docs.apeworx.io/ape-vyper
Keywords: ethereum,ape,vyper
Classifier: Development Status :: 5 - Production/Stable
Classifier: Intended Audience :: Developers
Classifier: Natural Language :: English
Classifier: Operating System :: MacOS
Classifier: Operating System :: POSIX
Classifier: Programming Language :: Python :: 3
Classifier: Programming Language :: Python :: 3.10
Classifier: Programming Language :: Python :: 3.11
Classifier: Programming Language :: Python :: 3.12
Classifier: Programming Language :: Python :: 3.13
Classifier: Programming Language :: Python :: 3.14
Requires-Python: <4,>=3.10
License-File: LICENSE
Requires-Dist: eth-ape<0.9,>=0.8.25
Requires-Dist: ethpm-types
Requires-Dist: tqdm
Requires-Dist: vvm<0.4,>=0.2.0
Requires-Dist: vyper<0.5,>=0.3.7
Dynamic: license-file
